kira/__init__.py
kira/generate.py
kira/model_args.py
kira/tokenizer.py
kira/train.py
kira/models/kira/__init__.py
kira/models/kira/kira.py
kira/models/llama/__init__.py
kira/models/llama/download.sh
kira/models/llama/llama2.py
kira/models/mamba/__init__.py
kira/models/mamba/mamba.py
kira/modules/__init__.py
kira/modules/mha.py
kira/modules/rope_embeddings.py
kira_llm-0.2.0.dist-info/METADATA
kira_llm-0.2.0.dist-info/WHEEL
kira_llm-0.2.0.dist-info/RECORD
