Metadata-Version: 2.1
Name: kira_llm
Version: 0.2.0
Summary: That's right, I'm Kira ✍️
Author-email: "Artur A. Galstyan" <mail@arturgalstyan.dev>
License-Expression: MIT
Requires-Python: ~=3.10
Requires-Dist: beartype
Requires-Dist: equinox
Requires-Dist: fire
Requires-Dist: jax
Requires-Dist: jaxlib
Requires-Dist: jaxonloader
Requires-Dist: jaxtyping
Requires-Dist: loguru
Requires-Dist: matplotlib
Requires-Dist: nox
Requires-Dist: optax
Requires-Dist: pre-commit
Requires-Dist: pytest
Requires-Dist: tqdm
Requires-Dist: typing-extensions
Requires-Dist: wandb
